.gitignore
.gitmodules
CONTRIBUTING.md
LICENSE.txt
README.md
pyproject.toml
setup.py
.github/workflows/python-package-conda.yml
doc/Makefile
doc/conf.py
doc/index.rst
examples/exp_fitting.ipynb
examples/neuron_simulation.py
examples/release_model.py
examples/search_fit.py
examples/test_event_detection.py
examples/test_psp_fit.py
examples/test_psp_train_fit.py
examples/test_pulse_analysis.ipynb
neuroanalysis/__init__.py
neuroanalysis/baseline.py
neuroanalysis/event_detection.py
neuroanalysis/filter.py
neuroanalysis/miesnwb.py
neuroanalysis/spike_detection.py
neuroanalysis/stats.py
neuroanalysis/stimuli.py
neuroanalysis/synaptic_release.py
neuroanalysis/test_pulse.py
neuroanalysis/test_pulse_stack.py
neuroanalysis/units.py
neuroanalysis.egg-info/PKG-INFO
neuroanalysis.egg-info/SOURCES.txt
neuroanalysis.egg-info/dependency_links.txt
neuroanalysis.egg-info/requires.txt
neuroanalysis.egg-info/top_level.txt
neuroanalysis/analyzers/__init__.py
neuroanalysis/analyzers/analyzer.py
neuroanalysis/analyzers/baseline.py
neuroanalysis/analyzers/stim_pulse.py
neuroanalysis/data/__init__.py
neuroanalysis/data/dataset.py
neuroanalysis/data/loaders/__init__.py
neuroanalysis/data/loaders/acq4_dataset_loader.py
neuroanalysis/data/loaders/loaders.py
neuroanalysis/data/loaders/mies_dataset_loader.py
neuroanalysis/fitting/__init__.py
neuroanalysis/fitting/exp.py
neuroanalysis/fitting/fit_scale_offset.py
neuroanalysis/fitting/fitmodel.py
neuroanalysis/fitting/gaussian.py
neuroanalysis/fitting/psp.py
neuroanalysis/fitting/searchfit.py
neuroanalysis/fitting/sigmoid.py
neuroanalysis/neuronsim/__init__.py
neuroanalysis/neuronsim/components.py
neuroanalysis/neuronsim/mechanisms.py
neuroanalysis/neuronsim/model_cell.py
neuroanalysis/neuronsim/sim.py
neuroanalysis/tests/test_analyzers.py
neuroanalysis/tests/test_data.py
neuroanalysis/tests/test_event_detection.py
neuroanalysis/tests/test_exp_fit.py
neuroanalysis/tests/test_psp_fitting.py
neuroanalysis/tests/test_release_model.py
neuroanalysis/tests/test_spike_detection.py
neuroanalysis/tests/test_stimuli.py
neuroanalysis/tests/test_test_pulse.py
neuroanalysis/ui/__init__.py
neuroanalysis/ui/baseline.py
