Metadata-Version: 2.1
Name: neuroanalysis
Version: 0.0.7
Summary: Functions and modular user interface tools for analysis of patch clamp experiment data.
Author-email: Luke Campagnola <lukec@alleninstitute.org>
License: Copyright (c) 2016- Allen Institute for Brain Science
Project-URL: homepage, https://github.com/AllenInstitute/neuroanalysis
Project-URL: issues, https://github.com/AllenInstitute/neuroanalysis/issues
Keywords: neuroscience,analysis,neurodata,without,borders,nwb
Classifier: Development Status :: 4 - Beta
Classifier: Environment :: Other Environment
Classifier: Intended Audience :: Science/Research
Classifier: License :: OSI Approved :: MIT License
Classifier: Operating System :: OS Independent
Classifier: Programming Language :: Python :: 3
Classifier: Programming Language :: Python
Classifier: Topic :: Scientific/Engineering
Classifier: Topic :: Software Development :: Libraries :: Python Modules
License-File: LICENSE.txt
Requires-Dist: numpy
Requires-Dist: scipy
Requires-Dist: h5py
Requires-Dist: neuron
Provides-Extra: acq4
Requires-Dist: acq4; extra == "acq4"
Provides-Extra: jit
Requires-Dist: numba; extra == "jit"
Provides-Extra: mies
Provides-Extra: test
Requires-Dist: pytest; extra == "test"
Provides-Extra: ui
Requires-Dist: pyqtgraph; extra == "ui"
